fh_matplotlib/__init__.py
tests/__init__.py
tests/test_basics.py
tests/test_clicker.py
fh_matplotlib-0.0.4.dist-info/LICENSE
fh_matplotlib-0.0.4.dist-info/METADATA
fh_matplotlib-0.0.4.dist-info/WHEEL
fh_matplotlib-0.0.4.dist-info/top_level.txt
fh_matplotlib-0.0.4.dist-info/RECORD
