Metadata-Version: 2.1
Name: fh-matplotlib
Version: 0.0.4
Summary: Make is easy to use matplotlib in FastHTML
Author: Vincent D. Warmerdam
Provides-Extra: dev
License-File: LICENSE
